LICENSE
README.md
setup.py
functionlayer/__init__.py
functionlayer.egg-info/PKG-INFO
functionlayer.egg-info/SOURCES.txt
functionlayer.egg-info/dependency_links.txt
functionlayer.egg-info/requires.txt
functionlayer.egg-info/top_level.txt