Metadata-Version: 2.1
Name: functionlayer
Version: 0.0
Summary: Agent Layer
Author: Delip Rao
Author-email: deliprao@gmail.com
License-File: LICENSE
